shared_context/__init__.py
shared_context/application.py
shared_context/domain/__init__.py
shared_context/domain/events.py
shared_context/domain/model.py
shared_context/domain/service.py
shared_context/infrastructure/__init__.py
shared_context/infrastructure/api/__init__.py
shared_context/infrastructure/api/flask.py
shared_context/infrastructure/persistence/__init__.py
shared_context/infrastructure/persistence/sqlalchemy.py
ddd_shared_context_fdelgados-0.0.4.dist-info/LICENSE
ddd_shared_context_fdelgados-0.0.4.dist-info/METADATA
ddd_shared_context_fdelgados-0.0.4.dist-info/WHEEL
ddd_shared_context_fdelgados-0.0.4.dist-info/top_level.txt
ddd_shared_context_fdelgados-0.0.4.dist-info/RECORD
